zope/app/component/__init__.py
zope/app/component/configure.zcml
zope/app/component/contentdirective.py
zope/app/component/ftesting.zcml
zope/app/component/hooks.py
zope/app/component/i18n.py
zope/app/component/meta.zcml
zope/app/component/metaconfigure.py
zope/app/component/metadirectives.py
zope/app/component/site.py
zope/app/component/testing.py
zope/app/component/vocabulary.py
zope/app/component/browser/__init__.py
zope/app/component/browser/configure.zcml
zope/app/component/browser/ftesting.zcml
zope/app/component/browser/registration.pt
zope/app/component/browser/registration.py
zope/app/component/browser/site.rst
zope/app/component/browser/siteregistration.pt
zope/app/component/browser/tests/__init__.py
zope/app/component/browser/tests/test_site.py
zope/app/component/interfaces/__init__.py
zope/app/component/interfaces/registration.py
zope/app/component/interfaces/tests/__init__.py
zope/app/component/interfaces/tests/test_registration.py
zope/app/component/tests/__init__.py
zope/app/component/tests/test_bwc_imports.py
zope/app/component/tests/test_testing.py
zope_app_component-6.0.dist-info/licenses/LICENSE.txt
zope_app_component-6.0.dist-info/METADATA
zope_app_component-6.0.dist-info/WHEEL
zope_app_component-6.0.dist-info/top_level.txt
zope_app_component-6.0.dist-info/RECORD
